odoo/addons/account_operating_unit_access_all/README.rst
odoo/addons/account_operating_unit_access_all/__init__.py
odoo/addons/account_operating_unit_access_all/__manifest__.py
odoo/addons/account_operating_unit_access_all/i18n/account_operating_unit_access_all.pot
odoo/addons/account_operating_unit_access_all/i18n/it.po
odoo/addons/account_operating_unit_access_all/readme/CONFIGURE.md
odoo/addons/account_operating_unit_access_all/readme/CONTRIBUTORS.md
odoo/addons/account_operating_unit_access_all/readme/DESCRIPTION.md
odoo/addons/account_operating_unit_access_all/security/account_security.xml
odoo/addons/account_operating_unit_access_all/static/description/icon.png
odoo/addons/account_operating_unit_access_all/static/description/index.html
odoo_addon_account_operating_unit_access_all-17.0.1.0.0.3.dist-info/METADATA
odoo_addon_account_operating_unit_access_all-17.0.1.0.0.3.dist-info/WHEEL
odoo_addon_account_operating_unit_access_all-17.0.1.0.0.3.dist-info/top_level.txt
odoo_addon_account_operating_unit_access_all-17.0.1.0.0.3.dist-info/RECORD
